MANIFEST.in
setup.py
losanalyst/__init__.py
losanalyst.egg-info/PKG-INFO
losanalyst.egg-info/SOURCES.txt
losanalyst.egg-info/dependency_links.txt
losanalyst.egg-info/not-zip-safe
losanalyst.egg-info/requires.txt
losanalyst.egg-info/top_level.txt
losanalyst/classes/__init__.py
losanalyst/classes/los.py
losanalyst/classes/los_global.py
losanalyst/classes/los_local.py
losanalyst/classes/los_without_target.py
losanalyst/functions/__init__.py
losanalyst/functions/checks.py
losanalyst/functions/helpers.py
losanalyst/functions/los_field_names.py
losanalyst/tools/__init__.py
losanalyst/tools/analyze_los.py
losanalyst/tools/create_los.py
losanalyst/tools/extract_horizon_line.py
losanalyst/tools/extract_horizons.py