Metadata-Version: 1.0
Name: losanalyst
Version: 0.2.0
Summary: Line-of-Sight Analyst package
Home-page: https://github.com/JanCaha/los_analyst
Author: Jan Caha
Author-email: jan.caha@outlook.com
License: MIT
Platform: UNKNOWN
